thinking_injection/__init__.py
thinking_injection/context.py
thinking_injection/dependencies.py
thinking_injection/discovery.py
thinking_injection/guardeddict.py
thinking_injection/implementations.py
thinking_injection/injectable.py
thinking_injection/interfaces.py
thinking_injection/lifecycle.py
thinking_injection/ordering.py
thinking_injection/requirements.py
thinking_injection/scope.py
thinking_injection/typeset.py
thinking_programming/__init__.py
thinking_programming/callbacks.py
thinking_programming/outcome.py
thinking_programming/serialization.py
thinking_injection-0.0.1.dist-info/LICENSE
thinking_injection-0.0.1.dist-info/METADATA
thinking_injection-0.0.1.dist-info/WHEEL
thinking_injection-0.0.1.dist-info/top_level.txt
thinking_injection-0.0.1.dist-info/RECORD
