Metadata-Version: 2.1
Name: thinking-injection
Version: 0.0.1
Summary: DI framework
Author-email: Filip Malczak <filip.malczak@gmail.com>
License: MIT License
Project-URL: Homepage, https://github.com/FilipMalczak/thinking-injection
Keywords: thinking,dependency,injection,di
Classifier: License :: OSI Approved :: MIT License
Classifier: Programming Language :: Python
Classifier: Programming Language :: Python :: 3
Classifier: Topic :: Software Development :: Libraries
Classifier: Topic :: Software Development :: Libraries :: Application Frameworks
Classifier: Typing :: Typed
Requires-Python: >=3.12
License-File: LICENSE
Requires-Dist: thinking-modules>=0.0.4
Requires-Dist: thinking-runtime>=0.0.3
